{"json": {"headline": "", "type": "crossword", "copy": {"title": "Toughie Crossword No 3620", "id": 80326, "description": "", "publisher": "", "setter": "Sparks", "byline": "Sparks", "date-publish": "Friday, 16 January 2026", "date-publish-email": "16 January 2026", "date-publish-analytics": "2026/01/16 00:00 Friday", "date-release": "Thursday, 15 January 2026", "date-solution": "Thursday, 15 January 2026", "crosswordtype": "Toughie Crossword", "correctsolutionmessagetext": "", "previoussolutiontext": "", "previoussolutionlink": "", "type": "block", "gridsize": {"type": "Standard", "cols": "15", "rows": "15"}, "settings": {"solution_hashed": "9a57eba4e5d5f2d4a771ae3fd680f256", "solution": "CATCALL G R C V L R U CAMISOLEDILEMMA L A M R S D B WALLOPEDSTRIKE H  T U U A B RAINDOCTORWILL J T I  E E R ENAMELLED B C O  C L E WILDEMBANKMENT I O N L O  A TENACETAILWIND A D K U G N A UNCLEARRHETORIC T E G Y D W F MINDSET"}, "hints": {"Mark Errors": "0", "Solve Letter": "0", "Solve Word": "0", "Ask A Friend": "0"}, "words": [{"id": 1, "x": "1-7", "y": "1", "solution": "CATCALL"}, {"id": 2, "x": "8-15", "y": "2", "solution": "CAMISOLE"}, {"id": 3, "x": "1-7", "y": "3", "solution": "DILEMMA"}, {"id": 4, "x": "8-15", "y": "4", "solution": "WALLOPED"}, {"id": 5, "x": "1-6", "y": "5", "solution": "STRIKE"}, {"id": 6, "x": "6-15", "y": "6", "solution": "RAINDOCTOR"}, {"id": 7, "x": "1-4", "y": "7", "solution": "WILL"}, {"id": 8, "x": "4-12", "y": "8", "solution": "ENAMELLED"}, {"id": 9, "x": "12-15", "y": "9", "solution": "WILD"}, {"id": 10, "x": "1-10", "y": "10", "solution": "EMBANKMENT"}, {"id": 11, "x": "10-15", "y": "11", "solution": "TENACE"}, {"id": 12, "x": "1-8", "y": "12", "solution": "TAILWIND"}, {"id": 13, "x": "9-15", "y": "13", "solution": "UNCLEAR"}, {"id": 14, "x": "1-8", "y": "14", "solution": "RHETORIC"}, {"id": 15, "x": "9-15", "y": "15", "solution": "MINDSET"}, {"id": 16, "x": "2", "y": "1-8", "solution": "ALISTAIR"}, {"id": 17, "x": "4", "y": "1-8", "solution": "CREDIBLE"}, {"id": 18, "x": "6", "y": "1-10", "solution": "LUMBERJACK"}, {"id": 19, "x": "9", "y": "1-4", "solution": "GALA"}, {"id": 20, "x": "11", "y": "1-6", "solution": "RIALTO"}, {"id": 21, "x": "13", "y": "1-7", "solution": "COMPUTE"}, {"id": 22, "x": "15", "y": "1-7", "solution": "VERDURE"}, {"id": 23, "x": "8", "y": "4-12", "solution": "WHITELEAD"}, {"id": 24, "x": "10", "y": "6-15", "solution": "DILETTANTI"}, {"id": 25, "x": "12", "y": "8-15", "solution": "DWINDLED"}, {"id": 26, "x": "14", "y": "8-15", "solution": "BLOCKAGE"}, {"id": 27, "x": "1", "y": "9-15", "solution": "CENTURY"}, {"id": 28, "x": "3", "y": "9-15", "solution": "OBLIGED"}, {"id": 29, "x": "5", "y": "10-15", "solution": "NOWNOW"}, {"id": 30, "x": "7", "y": "12-15", "solution": "NAIF"}], "clues": [{"name": "Clues", "title": "Across", "clues": [{"word": 1, "number": 1, "clue": "Covering several eventualities after hospital&rsquo;s suppressed complaint in theatre?", "format": "7", "length": 7, "answer": "CATCALL"}, {"word": 2, "number": 9, "clue": "Something eccentric: Penny once absconding in Tristan&rsquo;s beloved underwear", "format": "8", "length": 8, "answer": "CAMISOLE"}, {"word": 3, "number": 10, "clue": "Turned back cover &ndash; novel is <i>Catch-22</i>", "format": "7", "length": 7, "answer": "DILEMMA"}, {"word": 4, "number": 11, "clue": "Beaten in a vote count returned in 24 hours", "format": "8", "length": 8, "answer": "WALLOPED"}, {"word": 5, "number": 12, "clue": "Second means of transport on which one won&rsquo;t go to work", "format": "6", "length": 6, "answer": "STRIKE"}, {"word": 6, "number": 13, "clue": "Weatherman from radio torn about carbon cuts", "format": "4-6", "length": 10, "answer": "rain-doctor"}, {"word": 7, "number": 15, "clue": "Desire progressive characters in <i>When Eight Bells Toll</i>", "format": "4", "length": 4, "answer": "WILL"}, {"word": 8, "number": 16, "clue": "Superficially glossy fashion magazine covering famous daughter", "format": "9", "length": 9, "answer": "ENAMELLED"}, {"word": 9, "number": 21, "clue": "Passionate with 11 Down upon discarding braces regularly", "format": "4", "length": 4, "answer": "WILD"}, {"word": 10, "number": 22, "clue": "Rely on measure used by police force sealing north London station", "format": "10", "length": 10, "answer": "EMBANKMENT"}, {"word": 11, "number": 24, "clue": "Combination of two cards?", "format": "6", "length": 6, "answer": "TENACE"}, {"word": 12, "number": 25, "clue": "Turn on dog that could improve sprint time?", "format": "8", "length": 8, "answer": "TAILWIND"}, {"word": 13, "number": 27, "clue": "Ambiguous small shift in possessing WMD?", "format": "7", "length": 7, "answer": "UNCLEAR"}, {"word": 14, "number": 28, "clue": "Showy expression using &ldquo;thrice&rdquo; or otherwise", "format": "8", "length": 8, "answer": "RHETORIC"}, {"word": 15, "number": 29, "clue": "Attitude encountered when taking in godson, essentially", "format": "7", "length": 7, "answer": "MINDSET"}]}, {"name": "Clues", "title": "Down", "clues": [{"word": 16, "number": 2, "clue": "Chap conveying bearing of celebrity?", "format": "8", "length": 8, "answer": "Alistair"}, {"word": 17, "number": 3, "clue": "Trustworthy contractor&rsquo;s housing OK for consumer", "format": "8", "length": 8, "answer": "CREDIBLE"}, {"word": 18, "number": 4, "clue": "Start of <i>Little Brown Jug</i> initially accompanies naked feller?", "format": "10", "length": 10, "answer": "LUMBERJACK"}, {"word": 19, "number": 5, "clue": "Fair delay upset arrivals to begin with", "format": "4", "length": 4, "answer": "GALA"}, {"word": 20, "number": 6, "clue": "Part of Venice trip&rsquo;s centrepiece scored quite highly?", "format": "6", "length": 6, "answer": "Rialto"}, {"word": 21, "number": 7, "clue": "Hard cheese about backing up estimate", "format": "7", "length": 7, "answer": "COMPUTE"}, {"word": 22, "number": 8, "clue": "Engraver (D&uuml;rer) captures green vegetation", "format": "7", "length": 7, "answer": "VERDURE"}, {"word": 23, "number": 11, "clue": "Wine guide identifies something found in paint!", "format": "5,4", "length": 9, "answer": "white lead"}, {"word": 24, "number": 14, "clue": "Superficial arty types, ultimately deluded, allowed to be taken in by fake Titian", "format": "10", "length": 10, "answer": "DILETTANTI"}, {"word": 25, "number": 17, "clue": "Did Peter out of victory in major cup having played first", "format": "8", "length": 8, "answer": "DWINDLED"}, {"word": 26, "number": 18, "clue": "What might result in foul backlog above base of pipe", "format": "8", "length": 8, "answer": "BLOCKAGE"}, {"word": 27, "number": 19, "clue": "Milestone score that&rsquo;s not raised?", "format": "7", "length": 7, "answer": "CENTURY"}, {"word": 28, "number": 20, "clue": "Bound dictionary left in large stores? On the contrary", "format": "7", "length": 7, "answer": "OBLIGED"}, {"word": 29, "number": 23, "clue": "Don&rsquo;t bicker &ndash; you&rsquo;ve got two presents", "format": "3,3", "length": 6, "answer": "now now"}, {"word": 30, "number": 26, "clue": "Ingenuous climbing devotee one stops", "format": "4", "length": 4, "answer": "NAIF"}]}], "date-epoch": "1768521600"}, "options": [], "grid": [[{"SquareID": 1, "Number": "1", "Blank": "", "WordAcrossID": 1, "WordDownID": "", "Letter": "C"}, {"SquareID": 2, "Number": "2", "Blank": "", "WordAcrossID": 1, "WordDownID": 16, "Letter": "A"}, {"SquareID": 3, "Number": "", "Blank": "", "WordAcrossID": 1, "WordDownID": "", "Letter": "T"}, {"SquareID": 4, "Number": "3", "Blank": "", "WordAcrossID": 1, "WordDownID": 17, "Letter": "C"}, {"SquareID": 5, "Number": "", "Blank": "", "WordAcrossID": 1, "WordDownID": "", "Letter": "A"}, {"SquareID": 6, "Number": "4", "Blank": "", "WordAcrossID": 1, "WordDownID": 18, "Letter": "L"}, {"SquareID": 7, "Number": "", "Blank": "", "WordAcrossID": 1, "WordDownID": "", "Letter": "L"}, {"SquareID": 8, "Number": "", "Blank": "blank", "WordAcrossID": "", "WordDownID": "", "Letter": ""}, {"SquareID": 9, "Number": "5", "Blank": "", "WordAcrossID": "", "WordDownID": 19, "Letter": "G"}, {"SquareID": 10, "Number": "", "Blank": "blank", "WordAcrossID": "", "WordDownID": "", "Letter": ""}, {"SquareID": 11, "Number": "6", "Blank": "", "WordAcrossID": "", "WordDownID": 20, "Letter": "R"}, {"SquareID": 12, "Number": "", "Blank": "blank", "WordAcrossID": "", "WordDownID": "", "Letter": ""}, {"SquareID": 13, "Number": "7", "Blank": "", "WordAcrossID": "", "WordDownID": 21, "Letter": "C"}, {"SquareID": 14, "Number": "", "Blank": "blank", "WordAcrossID": "", "WordDownID": "", "Letter": ""}, {"SquareID": 15, "Number": "8", "Blank": "", "WordAcrossID": "", "WordDownID": 22, "Letter": "V"}], [{"SquareID": 16, "Number": "", "Blank": "blank", "WordAcrossID": "", "WordDownID": "", "Letter": ""}, {"SquareID": 17, "Number": "", "Blank": "", "WordAcrossID": "", "WordDownID": 16, "Letter": "L"}, {"SquareID": 18, "Number": "", "Blank": "blank", "WordAcrossID": "", "WordDownID": "", "Letter": ""}, {"SquareID": 19, "Number": "", "Blank": "", "WordAcrossID": "", "WordDownID": 17, "Letter": "R"}, {"SquareID": 20, "Number": "", "Blank": "blank", "WordAcrossID": "", "WordDownID": "", "Letter": ""}, {"SquareID": 21, "Number": "", "Blank": "", "WordAcrossID": "", "WordDownID": 18, "Letter": "U"}, {"SquareID": 22, "Number": "", "Blank": "blank", "WordAcrossID": "", "WordDownID": "", "Letter": ""}, {"SquareID": 23, "Number": "9", "Blank": "", "WordAcrossID": 2, "WordDownID": "", "Letter": "C"}, {"SquareID": 24, "Number": "", "Blank": "", "WordAcrossID": 2, "WordDownID": 19, "Letter": "A"}, {"SquareID": 25, "Number": "", "Blank": "", "WordAcrossID": 2, "WordDownID": "", "Letter": "M"}, {"SquareID": 26, "Number": "", "Blank": "", "WordAcrossID": 2, "WordDownID": 20, "Letter": "I"}, {"SquareID": 27, "Number": "", "Blank": "", "WordAcrossID": 2, "WordDownID": "", "Letter": "S"}, {"SquareID": 28, "Number": "", "Blank": "", "WordAcrossID": 2, "WordDownID": 21, "Letter": "O"}, {"SquareID": 29, "Number": "", "Blank": "", "WordAcrossID": 2, "WordDownID": "", "Letter": "L"}, {"SquareID": 30, "Number": "", "Blank": "", "WordAcrossID": 2, "WordDownID": 22, "Letter": "E"}], [{"SquareID": 31, "Number": "10", "Blank": "", "WordAcrossID": 3, "WordDownID": "", "Letter": "D"}, {"SquareID": 32, "Number": "", "Blank": "", "WordAcrossID": 3, "WordDownID": 16, "Letter": "I"}, {"SquareID": 33, "Number": "", "Blank": "", "WordAcrossID": 3, "WordDownID": "", "Letter": "L"}, {"SquareID": 34, "Number": "", "Blank": "", "WordAcrossID": 3, "WordDownID": 17, "Letter": "E"}, {"SquareID": 35, "Number": "", "Blank": "", "WordAcrossID": 3, "WordDownID": "", "Letter": "M"}, {"SquareID": 36, "Number": "", "Blank": "", "WordAcrossID": 3, "WordDownID": 18, "Letter": "M"}, {"SquareID": 37, "Number": "", "Blank": "", "WordAcrossID": 3, "WordDownID": "", "Letter": "A"}, {"SquareID": 38, "Number": "", "Blank": "blank", "WordAcrossID": "", "WordDownID": "", "Letter": ""}, {"SquareID": 39, "Number": "", "Blank": "", "WordAcrossID": "", "WordDownID": 19, "Letter": "L"}, {"SquareID": 40, "Number": "", "Blank": "blank", "WordAcrossID": "", "WordDownID": "", "Letter": ""}, {"SquareID": 41, "Number": "", "Blank": "", "WordAcrossID": "", "WordDownID": 20, "Letter": "A"}, {"SquareID": 42, "Number": "", "Blank": "blank", "WordAcrossID": "", "WordDownID": "", "Letter": ""}, {"SquareID": 43, "Number": "", "Blank": "", "WordAcrossID": "", "WordDownID": 21, "Letter": "M"}, {"SquareID": 44, "Number": "", "Blank": "blank", "WordAcrossID": "", "WordDownID": "", "Letter": ""}, {"SquareID": 45, "Number": "", "Blank": "", "WordAcrossID": "", "WordDownID": 22, "Letter": "R"}], [{"SquareID": 46, "Number": "", "Blank": "blank", "WordAcrossID": "", "WordDownID": "", "Letter": ""}, {"SquareID": 47, "Number": "", "Blank": "", "WordAcrossID": "", "WordDownID": 16, "Letter": "S"}, {"SquareID": 48, "Number": "", "Blank": "blank", "WordAcrossID": "", "WordDownID": "", "Letter": ""}, {"SquareID": 49, "Number": "", "Blank": "", "WordAcrossID": "", "WordDownID": 17, "Letter": "D"}, {"SquareID": 50, "Number": "", "Blank": "blank", "WordAcrossID": "", "WordDownID": "", "Letter": ""}, {"SquareID": 51, "Number": "", "Blank": "", "WordAcrossID": "", "WordDownID": 18, "Letter": "B"}, {"SquareID": 52, "Number": "", "Blank": "blank", "WordAcrossID": "", "WordDownID": "", "Letter": ""}, {"SquareID": 53, "Number": "11", "Blank": "", "WordAcrossID": 4, "WordDownID": 23, "Letter": "W"}, {"SquareID": 54, "Number": "", "Blank": "", "WordAcrossID": 4, "WordDownID": 19, "Letter": "A"}, {"SquareID": 55, "Number": "", "Blank": "", "WordAcrossID": 4, "WordDownID": "", "Letter": "L"}, {"SquareID": 56, "Number": "", "Blank": "", "WordAcrossID": 4, "WordDownID": 20, "Letter": "L"}, {"SquareID": 57, "Number": "", "Blank": "", "WordAcrossID": 4, "WordDownID": "", "Letter": "O"}, {"SquareID": 58, "Number": "", "Blank": "", "WordAcrossID": 4, "WordDownID": 21, "Letter": "P"}, {"SquareID": 59, "Number": "", "Blank": "", "WordAcrossID": 4, "WordDownID": "", "Letter": "E"}, {"SquareID": 60, "Number": "", "Blank": "", "WordAcrossID": 4, "WordDownID": 22, "Letter": "D"}], [{"SquareID": 61, "Number": "12", "Blank": "", "WordAcrossID": 5, "WordDownID": "", "Letter": "S"}, {"SquareID": 62, "Number": "", "Blank": "", "WordAcrossID": 5, "WordDownID": 16, "Letter": "T"}, {"SquareID": 63, "Number": "", "Blank": "", "WordAcrossID": 5, "WordDownID": "", "Letter": "R"}, {"SquareID": 64, "Number": "", "Blank": "", "WordAcrossID": 5, "WordDownID": 17, "Letter": "I"}, {"SquareID": 65, "Number": "", "Blank": "", "WordAcrossID": 5, "WordDownID": "", "Letter": "K"}, {"SquareID": 66, "Number": "", "Blank": "", "WordAcrossID": 5, "WordDownID": 18, "Letter": "E"}, {"SquareID": 67, "Number": "", "Blank": "blank", "WordAcrossID": "", "WordDownID": "", "Letter": ""}, {"SquareID": 68, "Number": "", "Blank": "", "WordAcrossID": "", "WordDownID": 23, "Letter": "H"}, {"SquareID": 69, "Number": "", "Blank": "blank", "WordAcrossID": "", "WordDownID": "", "Letter": ""}, {"SquareID": 70, "Number": "", "Blank": "blank", "WordAcrossID": "", "WordDownID": "", "Letter": ""}, {"SquareID": 71, "Number": "", "Blank": "", "WordAcrossID": "", "WordDownID": 20, "Letter": "T"}, {"SquareID": 72, "Number": "", "Blank": "blank", "WordAcrossID": "", "WordDownID": "", "Letter": ""}, {"SquareID": 73, "Number": "", "Blank": "", "WordAcrossID": "", "WordDownID": 21, "Letter": "U"}, {"SquareID": 74, "Number": "", "Blank": "blank", "WordAcrossID": "", "WordDownID": "", "Letter": ""}, {"SquareID": 75, "Number": "", "Blank": "", "WordAcrossID": "", "WordDownID": 22, "Letter": "U"}], [{"SquareID": 76, "Number": "", "Blank": "blank", "WordAcrossID": "", "WordDownID": "", "Letter": ""}, {"SquareID": 77, "Number": "", "Blank": "", "WordAcrossID": "", "WordDownID": 16, "Letter": "A"}, {"SquareID": 78, "Number": "", "Blank": "blank", "WordAcrossID": "", "WordDownID": "", "Letter": ""}, {"SquareID": 79, "Number": "", "Blank": "", "WordAcrossID": "", "WordDownID": 17, "Letter": "B"}, {"SquareID": 80, "Number": "", "Blank": "blank", "WordAcrossID": "", "WordDownID": "", "Letter": ""}, {"SquareID": 81, "Number": "13", "Blank": "", "WordAcrossID": 6, "WordDownID": 18, "Letter": "R"}, {"SquareID": 82, "Number": "", "Blank": "", "WordAcrossID": 6, "WordDownID": "", "Letter": "A"}, {"SquareID": 83, "Number": "", "Blank": "", "WordAcrossID": 6, "WordDownID": 23, "Letter": "I"}, {"SquareID": 84, "Number": "", "Blank": "", "WordAcrossID": 6, "WordDownID": "", "Letter": "N"}, {"SquareID": 85, "Number": "14", "Blank": "", "WordAcrossID": 6, "WordDownID": 24, "Letter": "D"}, {"SquareID": 86, "Number": "", "Blank": "", "WordAcrossID": 6, "WordDownID": 20, "Letter": "O"}, {"SquareID": 87, "Number": "", "Blank": "", "WordAcrossID": 6, "WordDownID": "", "Letter": "C"}, {"SquareID": 88, "Number": "", "Blank": "", "WordAcrossID": 6, "WordDownID": 21, "Letter": "T"}, {"SquareID": 89, "Number": "", "Blank": "", "WordAcrossID": 6, "WordDownID": "", "Letter": "O"}, {"SquareID": 90, "Number": "", "Blank": "", "WordAcrossID": 6, "WordDownID": 22, "Letter": "R"}], [{"SquareID": 91, "Number": "15", "Blank": "", "WordAcrossID": 7, "WordDownID": "", "Letter": "W"}, {"SquareID": 92, "Number": "", "Blank": "", "WordAcrossID": 7, "WordDownID": 16, "Letter": "I"}, {"SquareID": 93, "Number": "", "Blank": "", "WordAcrossID": 7, "WordDownID": "", "Letter": "L"}, {"SquareID": 94, "Number": "", "Blank": "", "WordAcrossID": 7, "WordDownID": 17, "Letter": "L"}, {"SquareID": 95, "Number": "", "Blank": "blank", "WordAcrossID": "", "WordDownID": "", "Letter": ""}, {"SquareID": 96, "Number": "", "Blank": "", "WordAcrossID": "", "WordDownID": 18, "Letter": "J"}, {"SquareID": 97, "Number": "", "Blank": "blank", "WordAcrossID": "", "WordDownID": "", "Letter": ""}, {"SquareID": 98, "Number": "", "Blank": "", "WordAcrossID": "", "WordDownID": 23, "Letter": "T"}, {"SquareID": 99, "Number": "", "Blank": "blank", "WordAcrossID": "", "WordDownID": "", "Letter": ""}, {"SquareID": 100, "Number": "", "Blank": "", "WordAcrossID": "", "WordDownID": 24, "Letter": "I"}, {"SquareID": 101, "Number": "", "Blank": "blank", "WordAcrossID": "", "WordDownID": "", "Letter": ""}, {"SquareID": 102, "Number": "", "Blank": "blank", "WordAcrossID": "", "WordDownID": "", "Letter": ""}, {"SquareID": 103, "Number": "", "Blank": "", "WordAcrossID": "", "WordDownID": 21, "Letter": "E"}, {"SquareID": 104, "Number": "", "Blank": "blank", "WordAcrossID": "", "WordDownID": "", "Letter": ""}, {"SquareID": 105, "Number": "", "Blank": "", "WordAcrossID": "", "WordDownID": 22, "Letter": "E"}], [{"SquareID": 106, "Number": "", "Blank": "blank", "WordAcrossID": "", "WordDownID": "", "Letter": ""}, {"SquareID": 107, "Number": "", "Blank": "", "WordAcrossID": "", "WordDownID": 16, "Letter": "R"}, {"SquareID": 108, "Number": "", "Blank": "blank", "WordAcrossID": "", "WordDownID": "", "Letter": ""}, {"SquareID": 109, "Number": "16", "Blank": "", "WordAcrossID": 8, "WordDownID": 17, "Letter": "E"}, {"SquareID": 110, "Number": "", "Blank": "", "WordAcrossID": 8, "WordDownID": "", "Letter": "N"}, {"SquareID": 111, "Number": "", "Blank": "", "WordAcrossID": 8, "WordDownID": 18, "Letter": "A"}, {"SquareID": 112, "Number": "", "Blank": "", "WordAcrossID": 8, "WordDownID": "", "Letter": "M"}, {"SquareID": 113, "Number": "", "Blank": "", "WordAcrossID": 8, "WordDownID": 23, "Letter": "E"}, {"SquareID": 114, "Number": "", "Blank": "", "WordAcrossID": 8, "WordDownID": "", "Letter": "L"}, {"SquareID": 115, "Number": "", "Blank": "", "WordAcrossID": 8, "WordDownID": 24, "Letter": "L"}, {"SquareID": 116, "Number": "", "Blank": "", "WordAcrossID": 8, "WordDownID": "", "Letter": "E"}, {"SquareID": 117, "Number": "17", "Blank": "", "WordAcrossID": 8, "WordDownID": 25, "Letter": "D"}, {"SquareID": 118, "Number": "", "Blank": "blank", "WordAcrossID": "", "WordDownID": "", "Letter": ""}, {"SquareID": 119, "Number": "18", "Blank": "", "WordAcrossID": "", "WordDownID": 26, "Letter": "B"}, {"SquareID": 120, "Number": "", "Blank": "blank", "WordAcrossID": "", "WordDownID": "", "Letter": ""}], [{"SquareID": 121, "Number": "19", "Blank": "", "WordAcrossID": "", "WordDownID": 27, "Letter": "C"}, {"SquareID": 122, "Number": "", "Blank": "blank", "WordAcrossID": "", "WordDownID": "", "Letter": ""}, {"SquareID": 123, "Number": "20", "Blank": "", "WordAcrossID": "", "WordDownID": 28, "Letter": "O"}, {"SquareID": 124, "Number": "", "Blank": "blank", "WordAcrossID": "", "WordDownID": "", "Letter": ""}, {"SquareID": 125, "Number": "", "Blank": "blank", "WordAcrossID": "", "WordDownID": "", "Letter": ""}, {"SquareID": 126, "Number": "", "Blank": "", "WordAcrossID": "", "WordDownID": 18, "Letter": "C"}, {"SquareID": 127, "Number": "", "Blank": "blank", "WordAcrossID": "", "WordDownID": "", "Letter": ""}, {"SquareID": 128, "Number": "", "Blank": "", "WordAcrossID": "", "WordDownID": 23, "Letter": "L"}, {"SquareID": 129, "Number": "", "Blank": "blank", "WordAcrossID": "", "WordDownID": "", "Letter": ""}, {"SquareID": 130, "Number": "", "Blank": "", "WordAcrossID": "", "WordDownID": 24, "Letter": "E"}, {"SquareID": 131, "Number": "", "Blank": "blank", "WordAcrossID": "", "WordDownID": "", "Letter": ""}, {"SquareID": 132, "Number": "21", "Blank": "", "WordAcrossID": 9, "WordDownID": 25, "Letter": "W"}, {"SquareID": 133, "Number": "", "Blank": "", "WordAcrossID": 9, "WordDownID": "", "Letter": "I"}, {"SquareID": 134, "Number": "", "Blank": "", "WordAcrossID": 9, "WordDownID": 26, "Letter": "L"}, {"SquareID": 135, "Number": "", "Blank": "", "WordAcrossID": 9, "WordDownID": "", "Letter": "D"}], [{"SquareID": 136, "Number": "22", "Blank": "", "WordAcrossID": 10, "WordDownID": 27, "Letter": "E"}, {"SquareID": 137, "Number": "", "Blank": "", "WordAcrossID": 10, "WordDownID": "", "Letter": "M"}, {"SquareID": 138, "Number": "", "Blank": "", "WordAcrossID": 10, "WordDownID": 28, "Letter": "B"}, {"SquareID": 139, "Number": "", "Blank": "", "WordAcrossID": 10, "WordDownID": "", "Letter": "A"}, {"SquareID": 140, "Number": "23", "Blank": "", "WordAcrossID": 10, "WordDownID": 29, "Letter": "N"}, {"SquareID": 141, "Number": "", "Blank": "", "WordAcrossID": 10, "WordDownID": 18, "Letter": "K"}, {"SquareID": 142, "Number": "", "Blank": "", "WordAcrossID": 10, "WordDownID": "", "Letter": "M"}, {"SquareID": 143, "Number": "", "Blank": "", "WordAcrossID": 10, "WordDownID": 23, "Letter": "E"}, {"SquareID": 144, "Number": "", "Blank": "", "WordAcrossID": 10, "WordDownID": "", "Letter": "N"}, {"SquareID": 145, "Number": "", "Blank": "", "WordAcrossID": 10, "WordDownID": 24, "Letter": "T"}, {"SquareID": 146, "Number": "", "Blank": "blank", "WordAcrossID": "", "WordDownID": "", "Letter": ""}, {"SquareID": 147, "Number": "", "Blank": "", "WordAcrossID": "", "WordDownID": 25, "Letter": "I"}, {"SquareID": 148, "Number": "", "Blank": "blank", "WordAcrossID": "", "WordDownID": "", "Letter": ""}, {"SquareID": 149, "Number": "", "Blank": "", "WordAcrossID": "", "WordDownID": 26, "Letter": "O"}, {"SquareID": 150, "Number": "", "Blank": "blank", "WordAcrossID": "", "WordDownID": "", "Letter": ""}], [{"SquareID": 151, "Number": "", "Blank": "", "WordAcrossID": "", "WordDownID": 27, "Letter": "N"}, {"SquareID": 152, "Number": "", "Blank": "blank", "WordAcrossID": "", "WordDownID": "", "Letter": ""}, {"SquareID": 153, "Number": "", "Blank": "", "WordAcrossID": "", "WordDownID": 28, "Letter": "L"}, {"SquareID": 154, "Number": "", "Blank": "blank", "WordAcrossID": "", "WordDownID": "", "Letter": ""}, {"SquareID": 155, "Number": "", "Blank": "", "WordAcrossID": "", "WordDownID": 29, "Letter": "O"}, {"SquareID": 156, "Number": "", "Blank": "blank", "WordAcrossID": "", "WordDownID": "", "Letter": ""}, {"SquareID": 157, "Number": "", "Blank": "blank", "WordAcrossID": "", "WordDownID": "", "Letter": ""}, {"SquareID": 158, "Number": "", "Blank": "", "WordAcrossID": "", "WordDownID": 23, "Letter": "A"}, {"SquareID": 159, "Number": "", "Blank": "blank", "WordAcrossID": "", "WordDownID": "", "Letter": ""}, {"SquareID": 160, "Number": "24", "Blank": "", "WordAcrossID": 11, "WordDownID": 24, "Letter": "T"}, {"SquareID": 161, "Number": "", "Blank": "", "WordAcrossID": 11, "WordDownID": "", "Letter": "E"}, {"SquareID": 162, "Number": "", "Blank": "", "WordAcrossID": 11, "WordDownID": 25, "Letter": "N"}, {"SquareID": 163, "Number": "", "Blank": "", "WordAcrossID": 11, "WordDownID": "", "Letter": "A"}, {"SquareID": 164, "Number": "", "Blank": "", "WordAcrossID": 11, "WordDownID": 26, "Letter": "C"}, {"SquareID": 165, "Number": "", "Blank": "", "WordAcrossID": 11, "WordDownID": "", "Letter": "E"}], [{"SquareID": 166, "Number": "25", "Blank": "", "WordAcrossID": 12, "WordDownID": 27, "Letter": "T"}, {"SquareID": 167, "Number": "", "Blank": "", "WordAcrossID": 12, "WordDownID": "", "Letter": "A"}, {"SquareID": 168, "Number": "", "Blank": "", "WordAcrossID": 12, "WordDownID": 28, "Letter": "I"}, {"SquareID": 169, "Number": "", "Blank": "", "WordAcrossID": 12, "WordDownID": "", "Letter": "L"}, {"SquareID": 170, "Number": "", "Blank": "", "WordAcrossID": 12, "WordDownID": 29, "Letter": "W"}, {"SquareID": 171, "Number": "", "Blank": "", "WordAcrossID": 12, "WordDownID": "", "Letter": "I"}, {"SquareID": 172, "Number": "26", "Blank": "", "WordAcrossID": 12, "WordDownID": 30, "Letter": "N"}, {"SquareID": 173, "Number": "", "Blank": "", "WordAcrossID": 12, "WordDownID": 23, "Letter": "D"}, {"SquareID": 174, "Number": "", "Blank": "blank", "WordAcrossID": "", "WordDownID": "", "Letter": ""}, {"SquareID": 175, "Number": "", "Blank": "", "WordAcrossID": "", "WordDownID": 24, "Letter": "A"}, {"SquareID": 176, "Number": "", "Blank": "blank", "WordAcrossID": "", "WordDownID": "", "Letter": ""}, {"SquareID": 177, "Number": "", "Blank": "", "WordAcrossID": "", "WordDownID": 25, "Letter": "D"}, {"SquareID": 178, "Number": "", "Blank": "blank", "WordAcrossID": "", "WordDownID": "", "Letter": ""}, {"SquareID": 179, "Number": "", "Blank": "", "WordAcrossID": "", "WordDownID": 26, "Letter": "K"}, {"SquareID": 180, "Number": "", "Blank": "blank", "WordAcrossID": "", "WordDownID": "", "Letter": ""}], [{"SquareID": 181, "Number": "", "Blank": "", "WordAcrossID": "", "WordDownID": 27, "Letter": "U"}, {"SquareID": 182, "Number": "", "Blank": "blank", "WordAcrossID": "", "WordDownID": "", "Letter": ""}, {"SquareID": 183, "Number": "", "Blank": "", "WordAcrossID": "", "WordDownID": 28, "Letter": "G"}, {"SquareID": 184, "Number": "", "Blank": "blank", "WordAcrossID": "", "WordDownID": "", "Letter": ""}, {"SquareID": 185, "Number": "", "Blank": "", "WordAcrossID": "", "WordDownID": 29, "Letter": "N"}, {"SquareID": 186, "Number": "", "Blank": "blank", "WordAcrossID": "", "WordDownID": "", "Letter": ""}, {"SquareID": 187, "Number": "", "Blank": "", "WordAcrossID": "", "WordDownID": 30, "Letter": "A"}, {"SquareID": 188, "Number": "", "Blank": "blank", "WordAcrossID": "", "WordDownID": "", "Letter": ""}, {"SquareID": 189, "Number": "27", "Blank": "", "WordAcrossID": 13, "WordDownID": "", "Letter": "U"}, {"SquareID": 190, "Number": "", "Blank": "", "WordAcrossID": 13, "WordDownID": 24, "Letter": "N"}, {"SquareID": 191, "Number": "", "Blank": "", "WordAcrossID": 13, "WordDownID": "", "Letter": "C"}, {"SquareID": 192, "Number": "", "Blank": "", "WordAcrossID": 13, "WordDownID": 25, "Letter": "L"}, {"SquareID": 193, "Number": "", "Blank": "", "WordAcrossID": 13, "WordDownID": "", "Letter": "E"}, {"SquareID": 194, "Number": "", "Blank": "", "WordAcrossID": 13, "WordDownID": 26, "Letter": "A"}, {"SquareID": 195, "Number": "", "Blank": "", "WordAcrossID": 13, "WordDownID": "", "Letter": "R"}], [{"SquareID": 196, "Number": "28", "Blank": "", "WordAcrossID": 14, "WordDownID": 27, "Letter": "R"}, {"SquareID": 197, "Number": "", "Blank": "", "WordAcrossID": 14, "WordDownID": "", "Letter": "H"}, {"SquareID": 198, "Number": "", "Blank": "", "WordAcrossID": 14, "WordDownID": 28, "Letter": "E"}, {"SquareID": 199, "Number": "", "Blank": "", "WordAcrossID": 14, "WordDownID": "", "Letter": "T"}, {"SquareID": 200, "Number": "", "Blank": "", "WordAcrossID": 14, "WordDownID": 29, "Letter": "O"}, {"SquareID": 201, "Number": "", "Blank": "", "WordAcrossID": 14, "WordDownID": "", "Letter": "R"}, {"SquareID": 202, "Number": "", "Blank": "", "WordAcrossID": 14, "WordDownID": 30, "Letter": "I"}, {"SquareID": 203, "Number": "", "Blank": "", "WordAcrossID": 14, "WordDownID": "", "Letter": "C"}, {"SquareID": 204, "Number": "", "Blank": "blank", "WordAcrossID": "", "WordDownID": "", "Letter": ""}, {"SquareID": 205, "Number": "", "Blank": "", "WordAcrossID": "", "WordDownID": 24, "Letter": "T"}, {"SquareID": 206, "Number": "", "Blank": "blank", "WordAcrossID": "", "WordDownID": "", "Letter": ""}, {"SquareID": 207, "Number": "", "Blank": "", "WordAcrossID": "", "WordDownID": 25, "Letter": "E"}, {"SquareID": 208, "Number": "", "Blank": "blank", "WordAcrossID": "", "WordDownID": "", "Letter": ""}, {"SquareID": 209, "Number": "", "Blank": "", "WordAcrossID": "", "WordDownID": 26, "Letter": "G"}, {"SquareID": 210, "Number": "", "Blank": "blank", "WordAcrossID": "", "WordDownID": "", "Letter": ""}], [{"SquareID": 211, "Number": "", "Blank": "", "WordAcrossID": "", "WordDownID": 27, "Letter": "Y"}, {"SquareID": 212, "Number": "", "Blank": "blank", "WordAcrossID": "", "WordDownID": "", "Letter": ""}, {"SquareID": 213, "Number": "", "Blank": "", "WordAcrossID": "", "WordDownID": 28, "Letter": "D"}, {"SquareID": 214, "Number": "", "Blank": "blank", "WordAcrossID": "", "WordDownID": "", "Letter": ""}, {"SquareID": 215, "Number": "", "Blank": "", "WordAcrossID": "", "WordDownID": 29, "Letter": "W"}, {"SquareID": 216, "Number": "", "Blank": "blank", "WordAcrossID": "", "WordDownID": "", "Letter": ""}, {"SquareID": 217, "Number": "", "Blank": "", "WordAcrossID": "", "WordDownID": 30, "Letter": "F"}, {"SquareID": 218, "Number": "", "Blank": "blank", "WordAcrossID": "", "WordDownID": "", "Letter": ""}, {"SquareID": 219, "Number": "29", "Blank": "", "WordAcrossID": 15, "WordDownID": "", "Letter": "M"}, {"SquareID": 220, "Number": "", "Blank": "", "WordAcrossID": 15, "WordDownID": 24, "Letter": "I"}, {"SquareID": 221, "Number": "", "Blank": "", "WordAcrossID": 15, "WordDownID": "", "Letter": "N"}, {"SquareID": 222, "Number": "", "Blank": "", "WordAcrossID": 15, "WordDownID": 25, "Letter": "D"}, {"SquareID": 223, "Number": "", "Blank": "", "WordAcrossID": 15, "WordDownID": "", "Letter": "S"}, {"SquareID": 224, "Number": "", "Blank": "", "WordAcrossID": 15, "WordDownID": 26, "Letter": "E"}, {"SquareID": 225, "Number": "", "Blank": "", "WordAcrossID": 15, "WordDownID": "", "Letter": "T"}]], "meta": {"pdf": "https://puzzlesdata.telegraph.co.uk/pdf/puzzles/toughie-crossword/toughie-crossword-80326.pdf", "variant": "Toughie Crossword", "slug": "toughie-crossword-no-3620", "id": "80326", "number": "3620", "description": null, "type": "crossword", "author": "Sparks", "difficulty": "Medium", "archive": "/archive.json", "related": ""}, "feedback": null, "sharing": {"email": {"body": "https://puzzlesdata.telegraph.co.uk/pdf/puzzles/toughie-crossword/toughie-crossword-80326.pdf"}, "print": {"url": "https://puzzlesdata.telegraph.co.uk/pdf/puzzles/toughie-crossword/toughie-crossword-80326.pdf"}}, "uris": {"img/intro/*": "img/intro/*"}}}